src/__init__.py
src/async_configuration_discovery.py
src/claude_memory_parser.py
src/cli_generate_file_context.py
src/cli_main.py
src/config_types.py
src/configuration_context.py
src/configuration_discovery.py
src/context_builder.py
src/context_generator.py
src/cursor_rules_parser.py
src/dependencies.py
src/errors.py
src/file_context_generator.py
src/file_context_types.py
src/file_selector.py
src/gemini_api_client.py
src/generate_code_review_context.py
src/git_utils.py
src/github_pr_integration.py
src/logging_config.py
src/meta_prompt_analyzer.py
src/meta_prompt_generator.py
src/model_config.json
src/model_config_manager.py
src/progress.py
src/server.py
src/task_list_parser.py
src/cache/__init__.py
src/cache/memory_cache.py
src/cache/sqlite_cache.py
src/cli/__init__.py
src/cli/init_command.py
src/config/loader.py
src/interfaces/__init__.py
src/interfaces/async_wrappers.py
src/interfaces/cache_protocol.py
src/interfaces/cached_filesystem.py
src/interfaces/cached_git_client.py
src/interfaces/filesystem.py
src/interfaces/filesystem_impl.py
src/interfaces/git_client.py
src/interfaces/git_client_impl.py
src/models/__init__.py
src/models/converters.py
src/models/review_context.py
src/models/review_mode.py
src/models/task_info.py
src/orchestrator/__init__.py
src/orchestrator/init_strategies.py
src/services/__init__.py
src/services/file_finder.py
src/strategies/__init__.py
src/strategies/base.py
src/strategies/factory.py
src/strategies/general.py
src/strategies/github_pr.py
src/strategies/task_driven.py
gemini_code_review_mcp-0.5.0.dist-info/METADATA
gemini_code_review_mcp-0.5.0.dist-info/WHEEL
gemini_code_review_mcp-0.5.0.dist-info/entry_points.txt
gemini_code_review_mcp-0.5.0.dist-info/licenses/LICENSE
gemini_code_review_mcp-0.5.0.dist-info/RECORD
